gcputils/__init__.py
gcputils/__main__.py
gcputils/bigquery.py
gcputils/datastore.py
gcputils/exceptions.py
gcputils/firestore.py
gcputils/project.py
gcputils/queue.py
gcputils/scheduler.py
gcputils/schemas.py
gcputils/storage.py
simple_gcp-1.0.1.dist-info/DESCRIPTION.rst
simple_gcp-1.0.1.dist-info/METADATA
simple_gcp-1.0.1.dist-info/RECORD
simple_gcp-1.0.1.dist-info/WHEEL
simple_gcp-1.0.1.dist-info/entry_points.txt
simple_gcp-1.0.1.dist-info/metadata.json
simple_gcp-1.0.1.dist-info/top_level.txt
