Metadata-Version: 2.0
Name: simple-gcp
Version: 1.0.1
Summary: Google Cloud Utilities for Python 3
Home-page: http://gitlab.ingaia.com.br/jose.almeida/chargebee-operations-api
Author: Jose Armando de Almeida Neto
Author-email: jose@armandoalmeida.com.br
License: MIT
Platform: UNKNOWN
Classifier: License :: OSI Approved :: MIT License
Classifier: Programming Language :: Python :: 3
Classifier: Programming Language :: Python :: 3.7
Requires-Dist: google-cloud-firestore
Requires-Dist: google-cloud-datastore
Requires-Dist: google-cloud-tasks
Requires-Dist: google-cloud-storage
Requires-Dist: google-cloud-bigquery
